storeadddddddasdfads/__init__.py
storeadddddddasdfads/pp.py
storeadddddddasdfads-30.0.0.dist-info/LICENSE
storeadddddddasdfads-30.0.0.dist-info/WHEEL
storeadddddddasdfads-30.0.0.dist-info/METADATA
storeadddddddasdfads-30.0.0.dist-info/RECORD
