Metadata-Version: 2.3
Name: storeadddddddasdfads
Version: 30.0.0
Summary: This is the example_package_stormedge module.
Author-email: liudi <test@qq.com>
Project-URL: Home, https://www.baidu.com
